{
   "agent": "AutobahnPython",
   "behavior": "OK",
   "behaviorClose": "OK",
   "case": 305,
   "closedByMe": true,
   "createStats": true,
   "createWirelog": true,
   "description": "Send text message with payload of length 65536 auto-fragmented with <b>autoFragmentSize = 1300</b>.",
   "droppedByMe": false,
   "duration": 4,
   "expectation": "Receive echo'ed text message (with payload as sent and transmitted frame counts as expected). Clean close with normal code.",
   "expected": {
      "OK": [
         [
            "message",
            "**************************************************************** ...",
            false
         ]
      ]
   },
   "expectedClose": {
      "closeCode": [
         1000
      ],
      "closedByMe": true,
      "requireClean": true
   },
   "failedByMe": false,
   "httpRequest": "GET / HTTP/1.1\r\nUser-Agent: AutobahnTestSuite/0.7.4-0.10.9\r\nHost: 127.0.0.1:9001\r\nUpgrade: WebSocket\r\nConnection: Upgrade\r\nPragma: no-cache\r\nCache-Control: no-cache\r\nSec-WebSocket-Key: HekBeqRBAOLKjfgcIIAN3Q==\r\nSec-WebSocket-Version: 13\r\n\r\n",
   "httpResponse": "HTTP/1.1 101 Switching Protocols\r\nconnection: Upgrade\r\ncontent-length: 0\r\nx-frame-options: SAMEORIGIN\r\ncontent-type: text/plain; charset=utf-8\r\nx-xss-protection: 1; mode=block\r\nx-content-type-options: nosniff\r\nupgrade: websocket\r\nsec-websocket-accept: 0RiNgcfjsuRuhduXgwKOqaaUZaU=\r\n\r\n",
   "id": "10.1.1",
   "isServer": false,
   "localCloseCode": 1000,
   "localCloseReason": null,
   "received": [
      [
         "message",
         "**************************************************************** ...",
         false
      ]
   ],
   "remoteCloseCode": 1000,
   "remoteCloseReason": null,
   "reportCompressionRatio": false,
   "reportTime": false,
   "result": "Actual events match at least one expected.",
   "resultClose": "Connection was properly closed",
   "rxFrameStats": {
      "1": 1,
      "8": 1
   },
   "rxOctetStats": {
      "4": 1,
      "10": 1,
      "284": 1,
      "65536": 1
   },
   "started": "2016-01-14T16:20:05.829Z",
   "trafficStats": null,
   "txFrameStats": {
      "0": 50,
      "1": 1,
      "8": 1
   },
   "txOctetStats": {
      "8": 1,
      "240": 1,
      "544": 1,
      "1308": 50
   },
   "wasClean": true,
   "wasCloseHandshakeTimeout": false,
   "wasNotCleanReason": null,
   "wasOpenHandshakeTimeout": false,
   "wasServerConnectionDropTimeout": false,
   "wirelog": [
      [
         "TO",
         [
            240,
            "474554202f20485454502f312e310d0a557365722d4167656e743a204175746f6261686e5465737453756974652f302e372e342d302e31302e390d0a486f7374 ..."
         ],
         false
      ],
      [
         "RO",
         [
            284,
            "485454502f312e312031303120537769746368696e672050726f746f636f6c730d0a636f6e6e656374696f6e3a20557067726164650d0a636f6e74656e742d6c ..."
         ]
      ],
      [
         "TF",
         [
            1300,
            "**************************************************************** ..."
         ],
         1,
         false,
         0,
         "4707e069",
         null,
         null,
         false
      ],
      [
         "TO",
         [
            1308,
            "01fe05144707e0696d2dca436d2dca436d2dca436d2dca436d2dca436d2dca436d2dca436d2dca436d2dca436d2dca436d2dca436d2dca436d2dca436d2dca43 ..."
         ],
         false
      ],
      [
         "TF",
         [
            1300,
            "**************************************************************** ..."
         ],
         0,
         false,
         0,
         "d819a307",
         null,
         null,
         false
      ],
      [
         "TO",
         [
            1308,
            "00fe0514d819a307f233892df233892df233892df233892df233892df233892df233892df233892df233892df233892df233892df233892df233892df233892d ..."
         ],
         false
      ],
      [
         "TF",
         [
            1300,
            "**************************************************************** ..."
         ],
         0,
         false,
         0,
         "4812630f",
         null,
         null,
         false
      ],
      [
         "TO",
         [
            1308,
            "00fe05144812630f6238492562384925623849256238492562384925623849256238492562384925623849256238492562384925623849256238492562384925 ..."
         ],
         false
      ],
      [
         "TF",
         [
            1300,
            "**************************************************************** ..."
         ],
         0,
         false,
         0,
         "c5c53810",
         null,
         null,
         false
      ],
      [
         "TO",
         [
            1308,
            "00fe0514c5c53810efef123aefef123aefef123aefef123aefef123aefef123aefef123aefef123aefef123aefef123aefef123aefef123aefef123aefef123a ..."
         ],
         false
      ],
      [
         "TF",
         [
            1300,
            "**************************************************************** ..."
         ],
         0,
         false,
         0,
         "3a77b54a",
         null,
         null,
         false
      ],
      [
         "TO",
         [
            1308,
            "00fe05143a77b54a105d9f60105d9f60105d9f60105d9f60105d9f60105d9f60105d9f60105d9f60105d9f60105d9f60105d9f60105d9f60105d9f60105d9f60 ..."
         ],
         false
      ],
      [
         "TF",
         [
            1300,
            "**************************************************************** ..."
         ],
         0,
         false,
         0,
         "1449b32d",
         null,
         null,
         false
      ],
      [
         "TO",
         [
            1308,
            "00fe05141449b32d3e6399073e6399073e6399073e6399073e6399073e6399073e6399073e6399073e6399073e6399073e6399073e6399073e6399073e639907 ..."
         ],
         false
      ],
      [
         "TF",
         [
            1300,
            "**************************************************************** ..."
         ],
         0,
         false,
         0,
         "02259079",
         null,
         null,
         false
      ],
      [
         "TO",
         [
            1308,
            "00fe051402259079280fba53280fba53280fba53280fba53280fba53280fba53280fba53280fba53280fba53280fba53280fba53280fba53280fba53280fba53 ..."
         ],
         false
      ],
      [
         "TF",
         [
            1300,
            "**************************************************************** ..."
         ],
         0,
         false,
         0,
         "97f4fe85",
         null,
         null,
         false
      ],
      [
         "TO",
         [
            1308,
            "00fe051497f4fe85bdded4afbdded4afbdded4afbdded4afbdded4afbdded4afbdded4afbdded4afbdded4afbdded4afbdded4afbdded4afbdded4afbdded4af ..."
         ],
         false
      ],
      [
         "TF",
         [
            1300,
            "**************************************************************** ..."
         ],
         0,
         false,
         0,
         "11f09bb0",
         null,
         null,
         false
      ],
      [
         "TO",
         [
            1308,
            "00fe051411f09bb03bdab19a3bdab19a3bdab19a3bdab19a3bdab19a3bdab19a3bdab19a3bdab19a3bdab19a3bdab19a3bdab19a3bdab19a3bdab19a3bdab19a ..."
         ],
         false
      ],
      [
         "TF",
         [
            1300,
            "**************************************************************** ..."
         ],
         0,
         false,
         0,
         "fbc7d5f8",
         null,
         null,
         false
      ],
      [
         "TO",
         [
            1308,
            "00fe0514fbc7d5f8d1edffd2d1edffd2d1edffd2d1edffd2d1edffd2d1edffd2d1edffd2d1edffd2d1edffd2d1edffd2d1edffd2d1edffd2d1edffd2d1edffd2 ..."
         ],
         false
      ],
      [
         "TF",
         [
            1300,
            "**************************************************************** ..."
         ],
         0,
         false,
         0,
         "9e4e06ea",
         null,
         null,
         false
      ],
      [
         "TO",
         [
            1308,
            "00fe05149e4e06eab4642cc0b4642cc0b4642cc0b4642cc0b4642cc0b4642cc0b4642cc0b4642cc0b4642cc0b4642cc0b4642cc0b4642cc0b4642cc0b4642cc0 ..."
         ],
         false
      ],
      [
         "TF",
         [
            1300,
            "**************************************************************** ..."
         ],
         0,
         false,
         0,
         "5d679f42",
         null,
         null,
         false
      ],
      [
         "TO",
         [
            1308,
            "00fe05145d679f42774db568774db568774db568774db568774db568774db568774db568774db568774db568774db568774db568774db568774db568774db568 ..."
         ],
         false
      ],
      [
         "TF",
         [
            1300,
            "**************************************************************** ..."
         ],
         0,
         false,
         0,
         "aa28d5af",
         null,
         null,
         false
      ],
      [
         "TO",
         [
            1308,
            "00fe0514aa28d5af8002ff858002ff858002ff858002ff858002ff858002ff858002ff858002ff858002ff858002ff858002ff858002ff858002ff858002ff85 ..."
         ],
         false
      ],
      [
         "TF",
         [
            1300,
            "**************************************************************** ..."
         ],
         0,
         false,
         0,
         "404c8835",
         null,
         null,
         false
      ],
      [
         "TO",
         [
            1308,
            "00fe0514404c88356a66a21f6a66a21f6a66a21f6a66a21f6a66a21f6a66a21f6a66a21f6a66a21f6a66a21f6a66a21f6a66a21f6a66a21f6a66a21f6a66a21f ..."
         ],
         false
      ],
      [
         "TF",
         [
            1300,
            "**************************************************************** ..."
         ],
         0,
         false,
         0,
         "0483ad9e",
         null,
         null,
         false
      ],
      [
         "TO",
         [
            1308,
            "00fe05140483ad9e2ea987b42ea987b42ea987b42ea987b42ea987b42ea987b42ea987b42ea987b42ea987b42ea987b42ea987b42ea987b42ea987b42ea987b4 ..."
         ],
         false
      ],
      [
         "TF",
         [
            1300,
            "**************************************************************** ..."
         ],
         0,
         false,
         0,
         "347b56ea",
         null,
         null,
         false
      ],
      [
         "TO",
         [
            1308,
            "00fe0514347b56ea1e517cc01e517cc01e517cc01e517cc01e517cc01e517cc01e517cc01e517cc01e517cc01e517cc01e517cc01e517cc01e517cc01e517cc0 ..."
         ],
         false
      ],
      [
         "TF",
         [
            1300,
            "**************************************************************** ..."
         ],
         0,
         false,
         0,
         "51d42fa8",
         null,
         null,
         false
      ],
      [
         "TO",
         [
            1308,
            "00fe051451d42fa87bfe05827bfe05827bfe05827bfe05827bfe05827bfe05827bfe05827bfe05827bfe05827bfe05827bfe05827bfe05827bfe05827bfe0582 ..."
         ],
         false
      ],
      [
         "TF",
         [
            1300,
            "**************************************************************** ..."
         ],
         0,
         false,
         0,
         "cbb7baf2",
         null,
         null,
         false
      ],
      [
         "TO",
         [
            1308,
            "00fe0514cbb7baf2e19d90d8e19d90d8e19d90d8e19d90d8e19d90d8e19d90d8e19d90d8e19d90d8e19d90d8e19d90d8e19d90d8e19d90d8e19d90d8e19d90d8 ..."
         ],
         false
      ],
      [
         "TF",
         [
            1300,
            "**************************************************************** ..."
         ],
         0,
         false,
         0,
         "f289d13d",
         null,
         null,
         false
      ],
      [
         "TO",
         [
            1308,
            "00fe0514f289d13dd8a3fb17d8a3fb17d8a3fb17d8a3fb17d8a3fb17d8a3fb17d8a3fb17d8a3fb17d8a3fb17d8a3fb17d8a3fb17d8a3fb17d8a3fb17d8a3fb17 ..."
         ],
         false
      ],
      [
         "TF",
         [
            1300,
            "**************************************************************** ..."
         ],
         0,
         false,
         0,
         "da487b7e",
         null,
         null,
         false
      ],
      [
         "TO",
         [
            1308,
            "00fe0514da487b7ef0625154f0625154f0625154f0625154f0625154f0625154f0625154f0625154f0625154f0625154f0625154f0625154f0625154f0625154 ..."
         ],
         false
      ],
      [
         "TF",
         [
            1300,
            "**************************************************************** ..."
         ],
         0,
         false,
         0,
         "816938ff",
         null,
         null,
         false
      ],
      [
         "TO",
         [
            1308,
            "00fe0514816938ffab4312d5ab4312d5ab4312d5ab4312d5ab4312d5ab4312d5ab4312d5ab4312d5ab4312d5ab4312d5ab4312d5ab4312d5ab4312d5ab4312d5 ..."
         ],
         false
      ],
      [
         "TF",
         [
            1300,
            "**************************************************************** ..."
         ],
         0,
         false,
         0,
         "b8451cfc",
         null,
         null,
         false
      ],
      [
         "TO",
         [
            1308,
            "00fe0514b8451cfc926f36d6926f36d6926f36d6926f36d6926f36d6926f36d6926f36d6926f36d6926f36d6926f36d6926f36d6926f36d6926f36d6926f36d6 ..."
         ],
         false
      ],
      [
         "TF",
         [
            1300,
            "**************************************************************** ..."
         ],
         0,
         false,
         0,
         "a5a69d91",
         null,
         null,
         false
      ],
      [
         "TO",
         [
            1308,
            "00fe0514a5a69d918f8cb7bb8f8cb7bb8f8cb7bb8f8cb7bb8f8cb7bb8f8cb7bb8f8cb7bb8f8cb7bb8f8cb7bb8f8cb7bb8f8cb7bb8f8cb7bb8f8cb7bb8f8cb7bb ..."
         ],
         false
      ],
      [
         "TF",
         [
            1300,
            "**************************************************************** ..."
         ],
         0,
         false,
         0,
         "185a8879",
         null,
         null,
         false
      ],
      [
         "TO",
         [
            1308,
            "00fe0514185a88793270a2533270a2533270a2533270a2533270a2533270a2533270a2533270a2533270a2533270a2533270a2533270a2533270a2533270a253 ..."
         ],
         false
      ],
      [
         "TF",
         [
            1300,
            "**************************************************************** ..."
         ],
         0,
         false,
         0,
         "7bdb6d3e",
         null,
         null,
         false
      ],
      [
         "TO",
         [
            1308,
            "00fe05147bdb6d3e51f1471451f1471451f1471451f1471451f1471451f1471451f1471451f1471451f1471451f1471451f1471451f1471451f1471451f14714 ..."
         ],
         false
      ],
      [
         "TF",
         [
            1300,
            "**************************************************************** ..."
         ],
         0,
         false,
         0,
         "a365db26",
         null,
         null,
         false
      ],
      [
         "TO",
         [
            1308,
            "00fe0514a365db26894ff10c894ff10c894ff10c894ff10c894ff10c894ff10c894ff10c894ff10c894ff10c894ff10c894ff10c894ff10c894ff10c894ff10c ..."
         ],
         false
      ],
      [
         "TF",
         [
            1300,
            "**************************************************************** ..."
         ],
         0,
         false,
         0,
         "c61566f7",
         null,
         null,
         false
      ],
      [
         "TO",
         [
            1308,
            "00fe0514c61566f7ec3f4cddec3f4cddec3f4cddec3f4cddec3f4cddec3f4cddec3f4cddec3f4cddec3f4cddec3f4cddec3f4cddec3f4cddec3f4cddec3f4cdd ..."
         ],
         false
      ],
      [
         "TF",
         [
            1300,
            "**************************************************************** ..."
         ],
         0,
         false,
         0,
         "3c85ae3b",
         null,
         null,
         false
      ],
      [
         "TO",
         [
            1308,
            "00fe05143c85ae3b16af841116af841116af841116af841116af841116af841116af841116af841116af841116af841116af841116af841116af841116af8411 ..."
         ],
         false
      ],
      [
         "TF",
         [
            1300,
            "**************************************************************** ..."
         ],
         0,
         false,
         0,
         "36a84d98",
         null,
         null,
         false
      ],
      [
         "TO",
         [
            1308,
            "00fe051436a84d981c8267b21c8267b21c8267b21c8267b21c8267b21c8267b21c8267b21c8267b21c8267b21c8267b21c8267b21c8267b21c8267b21c8267b2 ..."
         ],
         false
      ],
      [
         "TF",
         [
            1300,
            "**************************************************************** ..."
         ],
         0,
         false,
         0,
         "1b177fb5",
         null,
         null,
         false
      ],
      [
         "TO",
         [
            1308,
            "00fe05141b177fb5313d559f313d559f313d559f313d559f313d559f313d559f313d559f313d559f313d559f313d559f313d559f313d559f313d559f313d559f ..."
         ],
         false
      ],
      [
         "TF",
         [
            1300,
            "**************************************************************** ..."
         ],
         0,
         false,
         0,
         "f1742276",
         null,
         null,
         false
      ],
      [
         "TO",
         [
            1308,
            "00fe0514f1742276db5e085cdb5e085cdb5e085cdb5e085cdb5e085cdb5e085cdb5e085cdb5e085cdb5e085cdb5e085cdb5e085cdb5e085cdb5e085cdb5e085c ..."
         ],
         false
      ],
      [
         "TF",
         [
            1300,
            "**************************************************************** ..."
         ],
         0,
         false,
         0,
         "ad826573",
         null,
         null,
         false
      ],
      [
         "TO",
         [
            1308,
            "00fe0514ad82657387a84f5987a84f5987a84f5987a84f5987a84f5987a84f5987a84f5987a84f5987a84f5987a84f5987a84f5987a84f5987a84f5987a84f59 ..."
         ],
         false
      ],
      [
         "TF",
         [
            1300,
            "**************************************************************** ..."
         ],
         0,
         false,
         0,
         "2b89a67a",
         null,
         null,
         false
      ],
      [
         "TO",
         [
            1308,
            "00fe05142b89a67a01a38c5001a38c5001a38c5001a38c5001a38c5001a38c5001a38c5001a38c5001a38c5001a38c5001a38c5001a38c5001a38c5001a38c50 ..."
         ],
         false
      ],
      [
         "TF",
         [
            1300,
            "**************************************************************** ..."
         ],
         0,
         false,
         0,
         "a71460c9",
         null,
         null,
         false
      ],
      [
         "TO",
         [
            1308,
            "00fe0514a71460c98d3e4ae38d3e4ae38d3e4ae38d3e4ae38d3e4ae38d3e4ae38d3e4ae38d3e4ae38d3e4ae38d3e4ae38d3e4ae38d3e4ae38d3e4ae38d3e4ae3 ..."
         ],
         false
      ],
      [
         "TF",
         [
            1300,
            "**************************************************************** ..."
         ],
         0,
         false,
         0,
         "11280f52",
         null,
         null,
         false
      ],
      [
         "TO",
         [
            1308,
            "00fe051411280f523b0225783b0225783b0225783b0225783b0225783b0225783b0225783b0225783b0225783b0225783b0225783b0225783b0225783b022578 ..."
         ],
         false
      ],
      [
         "TF",
         [
            1300,
            "**************************************************************** ..."
         ],
         0,
         false,
         0,
         "095152de",
         null,
         null,
         false
      ],
      [
         "TO",
         [
            1308,
            "00fe0514095152de237b78f4237b78f4237b78f4237b78f4237b78f4237b78f4237b78f4237b78f4237b78f4237b78f4237b78f4237b78f4237b78f4237b78f4 ..."
         ],
         false
      ],
      [
         "TF",
         [
            1300,
            "**************************************************************** ..."
         ],
         0,
         false,
         0,
         "775ec236",
         null,
         null,
         false
      ],
      [
         "TO",
         [
            1308,
            "00fe0514775ec2365d74e81c5d74e81c5d74e81c5d74e81c5d74e81c5d74e81c5d74e81c5d74e81c5d74e81c5d74e81c5d74e81c5d74e81c5d74e81c5d74e81c ..."
         ],
         false
      ],
      [
         "TF",
         [
            1300,
            "**************************************************************** ..."
         ],
         0,
         false,
         0,
         "df07aeef",
         null,
         null,
         false
      ],
      [
         "TO",
         [
            1308,
            "00fe0514df07aeeff52d84c5f52d84c5f52d84c5f52d84c5f52d84c5f52d84c5f52d84c5f52d84c5f52d84c5f52d84c5f52d84c5f52d84c5f52d84c5f52d84c5 ..."
         ],
         false
      ],
      [
         "TF",
         [
            1300,
            "**************************************************************** ..."
         ],
         0,
         false,
         0,
         "663a8cc4",
         null,
         null,
         false
      ],
      [
         "TO",
         [
            1308,
            "00fe0514663a8cc44c10a6ee4c10a6ee4c10a6ee4c10a6ee4c10a6ee4c10a6ee4c10a6ee4c10a6ee4c10a6ee4c10a6ee4c10a6ee4c10a6ee4c10a6ee4c10a6ee ..."
         ],
         false
      ],
      [
         "TF",
         [
            1300,
            "**************************************************************** ..."
         ],
         0,
         false,
         0,
         "3f87fed0",
         null,
         null,
         false
      ],
      [
         "TO",
         [
            1308,
            "00fe05143f87fed015add4fa15add4fa15add4fa15add4fa15add4fa15add4fa15add4fa15add4fa15add4fa15add4fa15add4fa15add4fa15add4fa15add4fa ..."
         ],
         false
      ],
      [
         "TF",
         [
            1300,
            "**************************************************************** ..."
         ],
         0,
         false,
         0,
         "0776e7e1",
         null,
         null,
         false
      ],
      [
         "TO",
         [
            1308,
            "00fe05140776e7e12d5ccdcb2d5ccdcb2d5ccdcb2d5ccdcb2d5ccdcb2d5ccdcb2d5ccdcb2d5ccdcb2d5ccdcb2d5ccdcb2d5ccdcb2d5ccdcb2d5ccdcb2d5ccdcb ..."
         ],
         false
      ],
      [
         "TF",
         [
            1300,
            "**************************************************************** ..."
         ],
         0,
         false,
         0,
         "76c82d33",
         null,
         null,
         false
      ],
      [
         "TO",
         [
            1308,
            "00fe051476c82d335ce207195ce207195ce207195ce207195ce207195ce207195ce207195ce207195ce207195ce207195ce207195ce207195ce207195ce20719 ..."
         ],
         false
      ],
      [
         "TF",
         [
            1300,
            "**************************************************************** ..."
         ],
         0,
         false,
         0,
         "bc219a79",
         null,
         null,
         false
      ],
      [
         "TO",
         [
            1308,
            "00fe0514bc219a79960bb053960bb053960bb053960bb053960bb053960bb053960bb053960bb053960bb053960bb053960bb053960bb053960bb053960bb053 ..."
         ],
         false
      ],
      [
         "TF",
         [
            1300,
            "**************************************************************** ..."
         ],
         0,
         false,
         0,
         "1d6e541c",
         null,
         null,
         false
      ],
      [
         "TO",
         [
            1308,
            "00fe05141d6e541c37447e3637447e3637447e3637447e3637447e3637447e3637447e3637447e3637447e3637447e3637447e3637447e3637447e3637447e36 ..."
         ],
         false
      ],
      [
         "TF",
         [
            1300,
            "**************************************************************** ..."
         ],
         0,
         false,
         0,
         "cf3d3121",
         null,
         null,
         false
      ],
      [
         "TO",
         [
            1308,
            "00fe0514cf3d3121e5171b0be5171b0be5171b0be5171b0be5171b0be5171b0be5171b0be5171b0be5171b0be5171b0be5171b0be5171b0be5171b0be5171b0b ..."
         ],
         false
      ],
      [
         "TF",
         [
            1300,
            "**************************************************************** ..."
         ],
         0,
         false,
         0,
         "e32bc316",
         null,
         null,
         false
      ],
      [
         "TO",
         [
            1308,
            "00fe0514e32bc316c901e93cc901e93cc901e93cc901e93cc901e93cc901e93cc901e93cc901e93cc901e93cc901e93cc901e93cc901e93cc901e93cc901e93c ..."
         ],
         false
      ],
      [
         "TF",
         [
            1300,
            "**************************************************************** ..."
         ],
         0,
         false,
         0,
         "f45a25a7",
         null,
         null,
         false
      ],
      [
         "TO",
         [
            1308,
            "00fe0514f45a25a7de700f8dde700f8dde700f8dde700f8dde700f8dde700f8dde700f8dde700f8dde700f8dde700f8dde700f8dde700f8dde700f8dde700f8d ..."
         ],
         false
      ],
      [
         "TF",
         [
            1300,
            "**************************************************************** ..."
         ],
         0,
         false,
         0,
         "e8379a60",
         null,
         null,
         false
      ],
      [
         "TO",
         [
            1308,
            "00fe0514e8379a60c21db04ac21db04ac21db04ac21db04ac21db04ac21db04ac21db04ac21db04ac21db04ac21db04ac21db04ac21db04ac21db04ac21db04a ..."
         ],
         false
      ],
      [
         "TF",
         [
            1300,
            "**************************************************************** ..."
         ],
         0,
         false,
         0,
         "cddf3b61",
         null,
         null,
         false
      ],
      [
         "TO",
         [
            1308,
            "00fe0514cddf3b61e7f5114be7f5114be7f5114be7f5114be7f5114be7f5114be7f5114be7f5114be7f5114be7f5114be7f5114be7f5114be7f5114be7f5114b ..."
         ],
         false
      ],
      [
         "TF",
         [
            1300,
            "**************************************************************** ..."
         ],
         0,
         false,
         0,
         "3ba44ed1",
         null,
         null,
         false
      ],
      [
         "TO",
         [
            1308,
            "00fe05143ba44ed1118e64fb118e64fb118e64fb118e64fb118e64fb118e64fb118e64fb118e64fb118e64fb118e64fb118e64fb118e64fb118e64fb118e64fb ..."
         ],
         false
      ],
      [
         "TF",
         [
            536,
            "**************************************************************** ..."
         ],
         0,
         true,
         0,
         "35208233",
         null,
         null,
         false
      ],
      [
         "TO",
         [
            544,
            "80fe0218352082331f0aa8191f0aa8191f0aa8191f0aa8191f0aa8191f0aa8191f0aa8191f0aa8191f0aa8191f0aa8191f0aa8191f0aa8191f0aa8191f0aa819 ..."
         ],
         false
      ],
      [
         "KL",
         10
      ],
      [
         "RO",
         [
            65536,
            "817f00000000000100002a2a2a2a2a2a2a2a2a2a2a2a2a2a2a2a2a2a2a2a2a2a2a2a2a2a2a2a2a2a2a2a2a2a2a2a2a2a2a2a2a2a2a2a2a2a2a2a2a2a2a2a2a2a ..."
         ]
      ],
      [
         "RO",
         [
            10,
            "2a2a2a2a2a2a2a2a2a2a"
         ]
      ],
      [
         "RF",
         [
            65536,
            "**************************************************************** ..."
         ],
         1,
         true,
         0,
         false,
         null
      ],
      [
         "TF",
         [
            2,
            "0x03e8"
         ],
         8,
         true,
         0,
         "55179560",
         null,
         null,
         false
      ],
      [
         "TO",
         [
            8,
            "88825517956056ff"
         ],
         false
      ],
      [
         "RO",
         [
            4,
            "880203e8"
         ]
      ],
      [
         "RF",
         [
            2,
            "0x03e8"
         ],
         8,
         true,
         0,
         false,
         null
      ]
   ]
}